AUTHORS.rst
CONTRIBUTING.rst
HISTORY.rst
LICENSE
MANIFEST.in
README.rst
setup.cfg
setup.py
docs/Makefile
docs/authors.rst
docs/conf.py
docs/contributing.rst
docs/history.rst
docs/index.rst
docs/installation.rst
docs/make.bat
docs/readme.rst
docs/usage.rst
figbed/__init__.py
figbed/figbed.py
figbed/show.py
figbed.egg-info/PKG-INFO
figbed.egg-info/SOURCES.txt
figbed.egg-info/dependency_links.txt
figbed.egg-info/entry_points.txt
figbed.egg-info/not-zip-safe
figbed.egg-info/requires.txt
figbed.egg-info/top_level.txt
tests/__init__.py
tests/test_figbed.py